setup.py
Maxis_EA_server.egg-info/PKG-INFO
Maxis_EA_server.egg-info/SOURCES.txt
Maxis_EA_server.egg-info/dependency_links.txt
Maxis_EA_server.egg-info/requires.txt
Maxis_EA_server.egg-info/top_level.txt
server/__init__.py
server/server.py
server/common/__init__.py
server/common/decorate.py
server/common/descriptor.py
server/common/errors.py
server/common/metaclasses.py
server/common/utils.py
server/common/variables.py
server/logger/__init__.py
server/logger/log_server.py
server/server/__init__.py
server/server/add_user.py
server/server/config_windows.py
server/server/core.py
server/server/remove_user.py
server/server/server_database.py
server/server/server_windows.py
server/server/stat_window.py