Metadata-Version: 1.0
Name: Maxis-EA-server
Version: 0.0.1
Summary: mess_server
Home-page: UNKNOWN
Author: Maxim Baranov
Author-email: maxis@ya.ru
License: UNKNOWN
Platform: UNKNOWN
